kalabash_pfxadmin_migrate/__init__.py
kalabash_pfxadmin_migrate/models.py
kalabash_pfxadmin_migrate/management/__init__.py
kalabash_pfxadmin_migrate/management/commands/__init__.py
kalabash_pfxadmin_migrate/management/commands/migrate_from_postfixadmin.py
kalabash_pfxadmin_migrate-1.1.5.dist-info/LICENSE
kalabash_pfxadmin_migrate-1.1.5.dist-info/METADATA
kalabash_pfxadmin_migrate-1.1.5.dist-info/WHEEL
kalabash_pfxadmin_migrate-1.1.5.dist-info/top_level.txt
kalabash_pfxadmin_migrate-1.1.5.dist-info/RECORD
